ArtisticLicense20.html
LICENSE.txt
MANIFEST.in
README.md
licenses-amendments.txt
setup.cfg
setup.py
testdata/__init__$py.class
testdata/__init__.py
testdata/__init__.pyc
testdata/__pycache__/__init__.cpython-36.pyc
testdata/__pycache__/__init__.cpython-38.pyc
testdata/__pycache__/__init__.pypy3-510.pyc
testdata/yapyutils_testdata/__init__$py.class
testdata/yapyutils_testdata/__init__.py
testdata/yapyutils_testdata/__init__.pyc
testdata/yapyutils_testdata/__pycache__/__init__.cpython-36.pyc
testdata/yapyutils_testdata/__pycache__/__init__.cpython-38.pyc
testdata/yapyutils_testdata/__pycache__/__init__.pypy3-510.pyc
testdata/yapyutils_testdata/files/file1.txt
testdata/yapyutils_testdata/files/dir0/file1.txt
testdata/yapyutils_testdata/files/dir0/dir00/file1.txt
testdata/yapyutils_testdata/files/dir0/dir00/file2.txt
testdata/yapyutils_testdata/files/dir0/dir01/file1.txt
testdata/yapyutils_testdata/files/dir0/dir01/file3.txt
testdata/yapyutils_testdata/files/dir1/file1.txt
testdata/yapyutils_testdata/testpackage/__init__.py
testdata/yapyutils_testdata/testpackage/__init__.pyc
testdata/yapyutils_testdata/testpackage/module1.py
testdata/yapyutils_testdata/testpackage/module1.pyc
testdata/yapyutils_testdata/testpackage/__pycache__/module1.cpython-38.pyc
testdata/yapyutils_testdata/testpackage/__pycache__/module1.pypy3-510.pyc
testdata/yapyutils_testdata/testpackage/subpackage0/__init__.py
testdata/yapyutils_testdata/testpackage/subpackage0/__init__.pyc
testdata/yapyutils_testdata/testpackage/subpackage0/submodule1.py
testdata/yapyutils_testdata/testpackage/subpackage0/submodule1.pyc
testdata/yapyutils_testdata/testpackage/subpackage0/submodule2.py
testdata/yapyutils_testdata/testpackage/subpackage0/submodule2.pyc
testdata/yapyutils_testdata/testpackage/subpackage1/__init__.py
testdata/yapyutils_testdata/testpackage/subpackage1/__init__.pyc
testdata/yapyutils_testdata/testpackage/subpackage1/submodule1.py
testdata/yapyutils_testdata/testpackage/subpackage1/submodule1.pyc
yapyutils.egg-info/PKG-INFO
yapyutils.egg-info/SOURCES.txt
yapyutils.egg-info/dependency_links.txt
yapyutils.egg-info/entry_points.txt
yapyutils.egg-info/not-zip-safe
yapyutils.egg-info/top_level.txt
