Metadata-Version: 1.2
Name: yapyutils
Version: 0.1.38
Summary: The 'yapyutils' package provides miscellaneous low-level Python utilities.
Home-page: https://sourceforge.net/projects/yapyutils/
Author: Arno-Can Uestuensoez
Author-email: acue_sf2@sourceforge.net
Maintainer: acue
Maintainer-email: acue_sf2@sourceforge.net
License: Artistic-License-2.0 + Forced-Fairplay-Constraints
Download-URL: https://sourceforge.net/projects/yapyutils/files/
Project-URL: home, https://sourceforge.net/projects/yapyutils
Project-URL: documents, https://yapyutils.sourceforge.io/
Project-URL: runtimerepo, https://pypi.org/project/yapyutils/
Project-URL: downloads, https://pypi.org/project/yapyutils/
Project-URL: downloads1, https://sourceforge.net/projects/yapyutils/
Project-URL: source, https://github.com/ArnoCan/yapyutils/
Project-URL: source1, https://sourceforge.net/projects/yapyutils/
Project-URL: source2, https://bitbucket.org/acue/yapyutils/
Project-URL: tracker, https://github.com/ArnoCan/yapyutils/issues
Keywords: ARM,GhostBSD,LinuxMint,Manjaro,TrueOS,Aix,Alpine,AlpineLinux,Arch,ArchLinux,ArchLinuxARM,Armbian,BSD,BlackArch,BlackArchLinux,CPython,CentOS,Cygwin,Darwin,Debian,Distribution,DragonFlyBSD,Fedora,FigureWrap,FreeBSD,Gentoo,HP-UX,IPython,ImageWrap,IronPython,Java,Java,Jython,Kali,KaliLinux,Linux,MacOS,Minix,Minx3,NetBSD,OS-X,OpenBSD,OpenSUSE,OpenWRT,PyPy,Python2,Python3,RHEL,Raspbian,ReactOS,SLES,Scriptin,SnowLeopard,Solaris,Sphinx,Sphinx,SuSE,SunOS,SunOS5,Ubuntu,Unix,WSL,WSL 1.0,WSL 2.0,
Platform: Aix
Platform: GhostBSD
Platform: LinuxMint
Platform: Manjaro
Platform: TrueOS
Platform: AlpineLinux
Platform: ArchLinux
Platform: ArchLinuxARM
Platform: Armbian
Platform: BlackArchLinux
Platform: CentOS
Platform: Cygwin
Platform: Darwin
Platform: Debian
Platform: DragonFlyBSD
Platform: FedoraLinux
Platform: FreeBSD
Platform: GentooLinux
Platform: HP-UX
Platform: KaliLinux
Platform: MacOS
Platform: Minix
Platform: Minx3
Platform: NetBSD
Platform: OS-X
Platform: OpenBSD
Platform: OpenSUSE
Platform: OpenWRT
Platform: RHEL
Platform: Raspbian
Platform: ReactOS
Platform: SLES
Platform: Solaris
Platform: SuSE
Platform: SunOS
Platform: SunOS5
Platform: Ubuntu
Platform: Unix
Platform: Windows10
Platform: Windows2003
Platform: Windows2008
Platform: Windows2010
Platform: Windows2012
Platform: Windows2016
Platform: Windows2019
Platform: Windows2019se
Platform: Windows7
Platform: Windows8
Platform: WindowsXP
Classifier: Framework :: Setuptools Plugin
Classifier: Development Status :: 4 - Beta
Classifier: Environment :: Console
Classifier: Environment :: MacOS X
Classifier: Environment :: Other Environment
Classifier: Environment :: Win32 (MS Windows)
Classifier: Environment :: X11 Applications
Classifier: Framework :: IPython
Classifier: Intended Audience :: Developers
Classifier: Intended Audience :: System Administrators
Classifier: License :: Free To Use But Restricted
Classifier: License :: OSI Approved :: Artistic License
Classifier: Natural Language :: English
Classifier: Operating System :: MacOS :: MacOS X
Classifier: Operating System :: Microsoft :: Windows
Classifier: Operating System :: Other OS
Classifier: Operating System :: POSIX
Classifier: Operating System :: POSIX :: BSD :: FreeBSD
Classifier: Operating System :: POSIX :: BSD :: OpenBSD
Classifier: Operating System :: POSIX :: Linux
Classifier: Operating System :: POSIX :: Other
Classifier: Operating System :: POSIX :: SunOS/Solaris
Classifier: Operating System :: Unix
Classifier: Programming Language :: C
Classifier: Programming Language :: C++
Classifier: Programming Language :: Cython
Classifier: Programming Language :: Java
Classifier: Programming Language :: Python
Classifier: Programming Language :: Python :: 2
Classifier: Programming Language :: Python :: 2.7
Classifier: Programming Language :: Python :: 3
Classifier: Programming Language :: Python :: 3.5
Classifier: Programming Language :: Python :: 3.6
Classifier: Programming Language :: Python :: 3.7
Classifier: Programming Language :: Python :: 3.8
Classifier: Programming Language :: Python :: 3.9
Classifier: Programming Language :: Python :: Implementation :: CPython
Classifier: Programming Language :: Python :: Implementation :: IronPython
Classifier: Programming Language :: Python :: Implementation :: Jython
Classifier: Programming Language :: Python :: Implementation :: PyPy
Classifier: Programming Language :: Unix Shell
Classifier: Topic :: Home Automation
Classifier: Topic :: Internet
Classifier: Topic :: Scientific/Engineering
Classifier: Topic :: Scientific/Engineering :: Interface Engine/Protocol Translator
Classifier: Topic :: Security
Classifier: Topic :: Software Development
Classifier: Topic :: Software Development :: Build Tools
Classifier: Topic :: Software Development :: Code Generators
Classifier: Topic :: Software Development :: Compilers
Classifier: Topic :: Software Development :: Debuggers
Classifier: Topic :: Software Development :: Embedded Systems
Classifier: Topic :: Software Development :: Interpreters
Classifier: Topic :: Software Development :: Libraries
Classifier: Topic :: Software Development :: Libraries :: Application Frameworks
Classifier: Topic :: Software Development :: Libraries :: Java Libraries
Classifier: Topic :: Software Development :: Libraries :: Python Modules
Classifier: Topic :: Software Development :: Libraries :: pygame
Classifier: Topic :: Software Development :: Pre-processors
Classifier: Topic :: Software Development :: Testing
Classifier: Topic :: System :: Distributed Computing
Classifier: Topic :: System :: Installation/Setup
Classifier: Topic :: System :: Logging
Classifier: Topic :: System :: Monitoring
Classifier: Topic :: System :: Networking
Classifier: Topic :: System :: Operating System
Classifier: Topic :: System :: Shells
Classifier: Topic :: System :: Software Distribution
Classifier: Topic :: System :: System Shells
Classifier: Topic :: System :: Systems Administration
Classifier: Topic :: Utilities
